sortlab/__init__.py
sortlab/bubblesort.py
sortlab/selectionsort.py
sortlab-0.4.0.dist-info/METADATA
sortlab-0.4.0.dist-info/WHEEL
sortlab-0.4.0.dist-info/top_level.txt
sortlab-0.4.0.dist-info/RECORD
