Metadata-Version: 2.4
Name: sortlab
Version: 0.4.0
Summary: A simple Python sorting library
Author: Lingeshwaran K V
Requires-Python: >=3.6
Dynamic: author
Dynamic: description
Dynamic: description-content-type
Dynamic: requires-python
Dynamic: summary
